pypecdp/__init__.py
pypecdp/browser.py
pypecdp/cdp_pipe.py
pypecdp/config.py
pypecdp/elem.py
pypecdp/logger.py
pypecdp/tab.py
pypecdp/util.py
pypecdp/cdp/README.md
pypecdp/cdp/__init__.py
pypecdp/cdp/accessibility.py
pypecdp/cdp/animation.py
pypecdp/cdp/audits.py
pypecdp/cdp/autofill.py
pypecdp/cdp/background_service.py
pypecdp/cdp/bluetooth_emulation.py
pypecdp/cdp/browser.py
pypecdp/cdp/cache_storage.py
pypecdp/cdp/cast.py
pypecdp/cdp/console.py
pypecdp/cdp/css.py
pypecdp/cdp/debugger.py
pypecdp/cdp/device_access.py
pypecdp/cdp/device_orientation.py
pypecdp/cdp/dom.py
pypecdp/cdp/dom_debugger.py
pypecdp/cdp/dom_snapshot.py
pypecdp/cdp/dom_storage.py
pypecdp/cdp/emulation.py
pypecdp/cdp/event_breakpoints.py
pypecdp/cdp/extensions.py
pypecdp/cdp/fed_cm.py
pypecdp/cdp/fetch.py
pypecdp/cdp/file_system.py
pypecdp/cdp/headless_experimental.py
pypecdp/cdp/heap_profiler.py
pypecdp/cdp/indexed_db.py
pypecdp/cdp/input_.py
pypecdp/cdp/inspector.py
pypecdp/cdp/io.py
pypecdp/cdp/layer_tree.py
pypecdp/cdp/log.py
pypecdp/cdp/media.py
pypecdp/cdp/memory.py
pypecdp/cdp/network.py
pypecdp/cdp/overlay.py
pypecdp/cdp/page.py
pypecdp/cdp/performance.py
pypecdp/cdp/performance_timeline.py
pypecdp/cdp/preload.py
pypecdp/cdp/profiler.py
pypecdp/cdp/pwa.py
pypecdp/cdp/py.typed
pypecdp/cdp/runtime.py
pypecdp/cdp/schema.py
pypecdp/cdp/security.py
pypecdp/cdp/service_worker.py
pypecdp/cdp/storage.py
pypecdp/cdp/system_info.py
pypecdp/cdp/target.py
pypecdp/cdp/tethering.py
pypecdp/cdp/tracing.py
pypecdp/cdp/util.py
pypecdp/cdp/web_audio.py
pypecdp/cdp/web_authn.py
pypecdp-0.5.1.dist-info/METADATA
pypecdp-0.5.1.dist-info/WHEEL
pypecdp-0.5.1.dist-info/licenses/LICENSE
pypecdp-0.5.1.dist-info/RECORD
