Metadata-Version: 2.4
Name: pypecdp
Version: 0.5.1
Summary: Async Chrome DevTools Protocol over POSIX pipes.
Project-URL: Homepage, https://github.com/sohaib17/pypecdp
Project-URL: Source, https://github.com/sohaib17/pypecdp
Project-URL: Issues, https://github.com/sohaib17/pypecdp/issues
Author: sohaib17
License: MIT License
License-File: LICENSE
Keywords: asyncio,automation,cdp,chrome,chromium,devtools,headless
Classifier: Development Status :: 3 - Alpha
Classifier: License :: OSI Approved :: MIT License
Classifier: Operating System :: POSIX :: Linux
Classifier: Programming Language :: Python :: 3 :: Only
Classifier: Programming Language :: Python :: 3.12
Classifier: Topic :: Internet :: WWW/HTTP
Classifier: Topic :: Software Development :: Libraries :: Python Modules
Requires-Python: >=3.12
Requires-Dist: deprecated>=1.2.0
Provides-Extra: dev
Requires-Dist: mypy>=1.5.0; extra == 'dev'
Requires-Dist: pytest-asyncio>=0.21.0; extra == 'dev'
Requires-Dist: pytest-cov>=4.1.0; extra == 'dev'
Requires-Dist: pytest>=7.4.0; extra == 'dev'
Requires-Dist: ruff>=0.1.0; extra == 'dev'
Provides-Extra: test
Requires-Dist: pytest-asyncio>=0.21.0; extra == 'test'
Requires-Dist: pytest-cov>=4.1.0; extra == 'test'
Requires-Dist: pytest>=7.4.0; extra == 'test'
